chancy/__init__.py
chancy/app.py
chancy/errors.py
chancy/hub.py
chancy/job.py
chancy/migrate.py
chancy/plugin.py
chancy/queue.py
chancy/rule.py
chancy/utils.py
chancy/worker.py
chancy/cli/__init__.py
chancy/cli/cli.py
chancy/cli/misc.py
chancy/cli/queue.py
chancy/cli/worker.py
chancy/contrib/__init__.py
chancy/contrib/django/__init__.py
chancy/contrib/django/admin.py
chancy/contrib/django/apps.py
chancy/contrib/django/auth.py
chancy/contrib/django/models.py
chancy/executors/__init__.py
chancy/executors/asyncex.py
chancy/executors/base.py
chancy/executors/process.py
chancy/executors/sub.py
chancy/executors/thread.py
chancy/migrations/v1.py
chancy/migrations/v2.py
chancy/migrations/v3.py
chancy/migrations/v4.py
chancy/migrations/v5.py
chancy/migrations/v6.py
chancy/plugins/__init__.py
chancy/plugins/leadership.py
chancy/plugins/pruner.py
chancy/plugins/recovery.py
chancy/plugins/reprioritize.py
chancy/plugins/retry.py
chancy/plugins/sentry.py
chancy/plugins/api/__init__.py
chancy/plugins/api/auth.py
chancy/plugins/api/core.py
chancy/plugins/api/plugin.py
chancy/plugins/api/dist/index.html
chancy/plugins/api/dist/logo_small.png
chancy/plugins/api/dist/assets/index-BeBUcUZz.js
chancy/plugins/api/dist/assets/index-DbAYIoBh.css
chancy/plugins/api/ui/README.md
chancy/plugins/api/ui/eslint.config.js
chancy/plugins/api/ui/index.html
chancy/plugins/api/ui/package-lock.json
chancy/plugins/api/ui/package.json
chancy/plugins/api/ui/tsconfig.app.json
chancy/plugins/api/ui/tsconfig.json
chancy/plugins/api/ui/tsconfig.node.json
chancy/plugins/api/ui/vite.config.ts
chancy/plugins/api/ui/public/logo_small.png
chancy/plugins/api/ui/src/App.css
chancy/plugins/api/ui/src/Layout.tsx
chancy/plugins/api/ui/src/index.scss
chancy/plugins/api/ui/src/main.tsx
chancy/plugins/api/ui/src/utils.tsx
chancy/plugins/api/ui/src/vite-env.d.ts
chancy/plugins/api/ui/src/components/Loading.tsx
chancy/plugins/api/ui/src/components/MetricCharts.tsx
chancy/plugins/api/ui/src/components/UpdatingTime.tsx
chancy-0.25.0.dist-info/METADATA
chancy-0.25.0.dist-info/WHEEL
chancy-0.25.0.dist-info/entry_points.txt
chancy-0.25.0.dist-info/licenses/LICENSE.md
chancy-0.25.0.dist-info/RECORD
