Metadata-Version: 2.4
Name: chancy
Version: 0.25.0
Summary: A simple and flexible job queue for Python
Project-URL: Repository, https://github.com/tktech/chancy
Project-URL: Documentation, https://tkte.ch/chancy/
Author-email: Tyler Kennedy <tk@tkte.ch>
License-File: LICENSE.md
Classifier: Development Status :: 4 - Beta
Classifier: Intended Audience :: Developers
Classifier: License :: OSI Approved :: MIT License
Classifier: Programming Language :: Python :: 3
Classifier: Programming Language :: Python :: 3.11
Classifier: Programming Language :: Python :: 3.12
Classifier: Programming Language :: Python :: 3.13
Requires-Python: >=3.11
Requires-Dist: psycopg[pool]>=3.2.1
Provides-Extra: cli
Requires-Dist: click; extra == 'cli'
Provides-Extra: cron
Requires-Dist: croniter; extra == 'cron'
Provides-Extra: django
Requires-Dist: django>=4.0.0; extra == 'django'
Provides-Extra: sub
Requires-Dist: interpreters-pep-734>=0.4.1; (python_version >= '3.13') and extra == 'sub'
Provides-Extra: web
Requires-Dist: itsdangerous; extra == 'web'
Requires-Dist: starlette; extra == 'web'
Requires-Dist: uvicorn[standard]; extra == 'web'
